puddle_ext/__init__.py
puddle_ext/cli.py
puddle_ext/convert.py
puddle_ext/view.py
tests/__init__.py
tests/test_convert.py
puddle_ext-1.3.dist-info/METADATA
puddle_ext-1.3.dist-info/WHEEL
puddle_ext-1.3.dist-info/entry_points.txt
puddle_ext-1.3.dist-info/top_level.txt
puddle_ext-1.3.dist-info/RECORD
