Metadata-Version: 2.1
Name: puddle_ext
Version: 1.3
Summary: A simple file extension converter.
Author-email: Jay Nash <jn202871@gmail.com>
Project-URL: Homepage, https://github.com/jn202871/puddle_ext
Project-URL: Issues, https://github.com/jn202871/puddle/issues_ext
Classifier: Programming Language :: Python :: 3
Classifier: License :: OSI Approved :: MIT License
Classifier: Operating System :: OS Independent
Requires-Python: >=3.8
